aws_cdk/aws_networkfirewall/__init__.py
aws_cdk/aws_networkfirewall/py.typed
aws_cdk/aws_networkfirewall/_jsii/__init__.py
aws_cdk/aws_networkfirewall/_jsii/aws-networkfirewall@1.204.0.jsii.tgz
aws_cdk.aws_networkfirewall-1.204.0.dist-info/LICENSE
aws_cdk.aws_networkfirewall-1.204.0.dist-info/METADATA
aws_cdk.aws_networkfirewall-1.204.0.dist-info/NOTICE
aws_cdk.aws_networkfirewall-1.204.0.dist-info/WHEEL
aws_cdk.aws_networkfirewall-1.204.0.dist-info/top_level.txt
aws_cdk.aws_networkfirewall-1.204.0.dist-info/RECORD
